LICENSE.txt
MANIFEST.in
README.md
setup.py
crest4/__init__.py
crest4/__main__.py
crest4/classify.py
crest4/databases.py
crest4/otu_tables.py
crest4/query.py
crest4.egg-info/PKG-INFO
crest4.egg-info/SOURCES.txt
crest4.egg-info/dependency_links.txt
crest4.egg-info/entry_points.txt
crest4.egg-info/requires.txt
crest4.egg-info/top_level.txt
crest4/tests/pytest.ini
crest4/tests/actualize_database/README.md
crest4/tests/actualize_database/run_test.py
crest4/tests/cmd_line_tool/README.md
crest4/tests/cmd_line_tool/run_test.py
crest4/tests/cmd_line_tool/two_seqs.fasta
crest4/tests/custom_database/README.md
crest4/tests/custom_database/run_test.py
crest4/tests/custom_database/two_seqs.fasta
crest4/tests/custom_database/custom/custom.fasta
crest4/tests/custom_database/custom/custom.map
crest4/tests/custom_database/custom/custom.names
crest4/tests/custom_database/custom/custom.tre
crest4/tests/custom_database/other_database/custom.fasta
crest4/tests/custom_database/other_database/custom.map
crest4/tests/custom_database/other_database/custom.names
crest4/tests/custom_database/other_database/custom.tre
crest4/tests/db_midori/README.md
crest4/tests/db_midori/run_test.py
crest4/tests/db_midori/seq.fasta
crest4/tests/db_mitofish/README.md
crest4/tests/db_mitofish/run_test.py
crest4/tests/db_mitofish/seq.fasta
crest4/tests/gio_hundred_seqs/expected_output/assigned.fasta
crest4/tests/ncbi_two_sequences/README.md
crest4/tests/ncbi_two_sequences/generate.py
crest4/tests/ncbi_two_sequences/run_test.py
crest4/tests/ncbi_two_sequences/two_seqs.fasta
crest4/tests/no_hits_sequence/README.md
crest4/tests/no_hits_sequence/no_hits.fasta
crest4/tests/no_hits_sequence/run_test.py
crest4/tests/precomputed_hits/README.md
crest4/tests/precomputed_hits/precomputed.hits
crest4/tests/precomputed_hits/run_test.py
crest4/tests/precomputed_hits/two_seqs.fasta
crest4/tests/readme_example_seq/README.md
crest4/tests/readme_example_seq/readme_test.fasta
crest4/tests/readme_example_seq/run_test.py
crest4/tests/score_drop_change/README.md
crest4/tests/score_drop_change/run_test.py
crest4/tests/score_drop_change/two_seqs.fasta
crest4/tests/vsearch_test/README.md
