Metadata-Version: 2.4
Name: crest4
Version: 4.3.8
Summary: The `crest4` python package can automatically assign taxonomic names to DNA sequences obtained from environmental sequencing.
Home-page: https://github.com/xapple/crest4/
Author: Anders Lanzén and Lucas Sinclair
Author-email: anders.lanzen@gmail.com
License: GPL3
Classifier: Topic :: Scientific/Engineering :: Bio-Informatics
Requires-Python: >=3.8
License-File: LICENSE.txt
Requires-Dist: autopaths>=1.5.0
Requires-Dist: optmagic>=1.1.0
Requires-Dist: plumbing>=2.10.4
Requires-Dist: fasta>=2.2.11
Requires-Dist: seqsearch>=2.2.1
Requires-Dist: biopython
Requires-Dist: rich
Requires-Dist: ete3
Requires-Dist: pandas
Requires-Dist: pytest
Dynamic: author
Dynamic: author-email
Dynamic: classifier
Dynamic: description
Dynamic: description-content-type
Dynamic: home-page
Dynamic: license
Dynamic: license-file
Dynamic: requires-dist
Dynamic: requires-python
Dynamic: summary
